README.md
setup.py
these.py
these.egg-info/PKG-INFO
these.egg-info/SOURCES.txt
these.egg-info/dependency_links.txt
these.egg-info/top_level.txt