Metadata-Version: 2.1
Name: these
Version: 0
Summary: The Markov Zenerator.
Home-page: https://github.com/brandtbucher/these
Author: Brandt Bucher
Author-email: brandtbucher@gmail.com
License: MIT
Keywords: Markov Zen this
Platform: UNKNOWN
